README.md
main.py
setup.py
misitebao.egg-info/PKG-INFO
misitebao.egg-info/SOURCES.txt
misitebao.egg-info/dependency_links.txt
misitebao.egg-info/entry_points.txt
misitebao.egg-info/top_level.txt