Metadata-Version: 2.1
Name: misitebao
Version: 1.0.2
Summary: Hi, I am Misite Bao.
Home-page: https://github.com/misitebao/misitebao
Author: Misite Bao
Author-email: i@misitebao.com
License: MIT License
Keywords: misitebao,misi
